{
  "timestamp": "2026-07-21T08:39:14.397951",
  "ranking": [
    {
      "category": "宠物智能-猫饮水机",
      "keyword_ru": "поилка для кошек автоматическая",
      "keyword_en": "automatic cat water fountain",
      "tags": [
        "蓝海",
        "全年品",
        "轻小件",
        "智能宠物增217%"
      ],
      "total_score": 11,
      "recommendation": "🔥 强烈推荐入场",
      "blue_ocean_index": 9.69,
      "dimensions": {
        "search_volume": 2,
        "search_volume_detail": "搜索结果155个",
        "avg_reviews": 2,
        "avg_reviews_detail": "TOP10平均评论12条",
        "seller_count": 2,
        "seller_count_detail": "TOP10卖家8家",
        "ozon_self": 1,
        "ozon_self_detail": "自营占比4.7%",
        "price_concentration": 2,
        "price_concentration_detail": "价格集中度0.54",
        "rating_variance": 1,
        "rating_variance_detail": "低评分占比28.4%",
        "rFBS_fitness": 1,
        "rFBS_fitness_detail": "标签: 蓝海, 全年品, 轻小件, 智能宠物增217%"
      },
      "metrics": {
        "total_search_results": 155,
        "avg_price": 317,
        "avg_reviews": 26,
        "avg_rating": 4.46,
        "unique_sellers": 15,
        "ozon_self_ratio": 0.047,
        "price_concentration": 0.5416,
        "low_rating_ratio": 0.2836,
        "top10_avg_reviews": 12,
        "top10_avg_rating": 4.34,
        "top10_seller_count": 8,
        "price_min": 134,
        "price_max": 2318
      }
    },
    {
      "category": "宠物清洁-除毛工具",
      "keyword_ru": "щетка для удаления шерсти",
      "keyword_en": "pet hair removal brush",
      "tags": [
        "刚需",
        "全年品",
        "轻小件",
        "换毛季高需求"
      ],
      "total_score": 11,
      "recommendation": "🔥 强烈推荐入场",
      "blue_ocean_index": 34.12,
      "dimensions": {
        "search_volume": 2,
        "search_volume_detail": "搜索结果546个",
        "avg_reviews": 2,
        "avg_reviews_detail": "TOP10平均评论31条",
        "seller_count": 2,
        "seller_count_detail": "TOP10卖家5家",
        "ozon_self": 1,
        "ozon_self_detail": "自营占比3.3%",
        "price_concentration": 2,
        "price_concentration_detail": "价格集中度0.52",
        "rating_variance": 1,
        "rating_variance_detail": "低评分占比27.1%",
        "rFBS_fitness": 1,
        "rFBS_fitness_detail": "标签: 刚需, 全年品, 轻小件, 换毛季高需求"
      },
      "metrics": {
        "total_search_results": 546,
        "avg_price": 670,
        "avg_reviews": 132,
        "avg_rating": 4.35,
        "unique_sellers": 15,
        "ozon_self_ratio": 0.0329,
        "price_concentration": 0.5166,
        "low_rating_ratio": 0.2714,
        "top10_avg_reviews": 31,
        "top10_avg_rating": 4.29,
        "top10_seller_count": 5,
        "price_min": 133,
        "price_max": 1947
      }
    },
    {
      "category": "家居收纳-冰箱收纳盒",
      "keyword_ru": "органайзер для холодильника",
      "keyword_en": "fridge organizer",
      "tags": [
        "蓝海",
        "全年刚需",
        "轻小件",
        "高复购"
      ],
      "total_score": 11,
      "recommendation": "🔥 强烈推荐入场",
      "blue_ocean_index": 34.22,
      "dimensions": {
        "search_volume": 2,
        "search_volume_detail": "搜索结果308个",
        "avg_reviews": 2,
        "avg_reviews_detail": "TOP10平均评论27条",
        "seller_count": 2,
        "seller_count_detail": "TOP10卖家9家",
        "ozon_self": 1,
        "ozon_self_detail": "自营占比6.4%",
        "price_concentration": 2,
        "price_concentration_detail": "价格集中度0.59",
        "rating_variance": 1,
        "rating_variance_detail": "低评分占比29.4%",
        "rFBS_fitness": 1,
        "rFBS_fitness_detail": "标签: 蓝海, 全年刚需, 轻小件, 高复购"
      },
      "metrics": {
        "total_search_results": 308,
        "avg_price": 844,
        "avg_reviews": 125,
        "avg_rating": 4.68,
        "unique_sellers": 8,
        "ozon_self_ratio": 0.0642,
        "price_concentration": 0.5929,
        "low_rating_ratio": 0.2937,
        "top10_avg_reviews": 27,
        "top10_avg_rating": 4.66,
        "top10_seller_count": 9,
        "price_min": 197,
        "price_max": 1708
      }
    },
    {
      "category": "厨房工具-食物温度计",
      "keyword_ru": "термометр для мяса электронный",
      "keyword_en": "electronic meat thermometer",
      "tags": [
        "蓝海",
        "全年品",
        "轻小件",
        "烧烤季热销"
      ],
      "total_score": 11,
      "recommendation": "🔥 强烈推荐入场",
      "blue_ocean_index": 32.67,
      "dimensions": {
        "search_volume": 2,
        "search_volume_detail": "搜索结果392个",
        "avg_reviews": 2,
        "avg_reviews_detail": "TOP10平均评论15条",
        "seller_count": 2,
        "seller_count_detail": "TOP10卖家8家",
        "ozon_self": 1,
        "ozon_self_detail": "自营占比7.8%",
        "price_concentration": 2,
        "price_concentration_detail": "价格集中度0.51",
        "rating_variance": 1,
        "rating_variance_detail": "低评分占比21.4%",
        "rFBS_fitness": 1,
        "rFBS_fitness_detail": "标签: 蓝海, 全年品, 轻小件, 烧烤季热销"
      },
      "metrics": {
        "total_search_results": 392,
        "avg_price": 822,
        "avg_reviews": 66,
        "avg_rating": 4.37,
        "unique_sellers": 11,
        "ozon_self_ratio": 0.0777,
        "price_concentration": 0.5134,
        "low_rating_ratio": 0.2137,
        "top10_avg_reviews": 15,
        "top10_avg_rating": 4.25,
        "top10_seller_count": 8,
        "price_min": 105,
        "price_max": 2509
      }
    },
    {
      "category": "厨房工具-多功能切菜器",
      "keyword_ru": "многофункциональная терка для овощей",
      "keyword_en": "multifunction vegetable grater",
      "tags": [
        "刚需",
        "全年品",
        "轻小件",
        "痛点解决"
      ],
      "total_score": 11,
      "recommendation": "🔥 强烈推荐入场",
      "blue_ocean_index": 13.82,
      "dimensions": {
        "search_volume": 2,
        "search_volume_detail": "搜索结果152个",
        "avg_reviews": 2,
        "avg_reviews_detail": "TOP10平均评论48条",
        "seller_count": 2,
        "seller_count_detail": "TOP10卖家7家",
        "ozon_self": 1,
        "ozon_self_detail": "自营占比3.0%",
        "price_concentration": 2,
        "price_concentration_detail": "价格集中度0.58",
        "rating_variance": 1,
        "rating_variance_detail": "低评分占比26.1%",
        "rFBS_fitness": 1,
        "rFBS_fitness_detail": "标签: 刚需, 全年品, 轻小件, 痛点解决"
      },
      "metrics": {
        "total_search_results": 152,
        "avg_price": 476,
        "avg_reviews": 95,
        "avg_rating": 4.32,
        "unique_sellers": 10,
        "ozon_self_ratio": 0.0305,
        "price_concentration": 0.5794,
        "low_rating_ratio": 0.261,
        "top10_avg_reviews": 48,
        "top10_avg_rating": 4.19,
        "top10_seller_count": 7,
        "price_min": 158,
        "price_max": 2500
      }
    },
    {
      "category": "车载冬季-加热毯",
      "keyword_ru": "автоодеяло с подогревом",
      "keyword_en": "car heated blanket",
      "tags": [
        "蓝海",
        "旺季10-2月",
        "轻小件",
        "需提前备货"
      ],
      "total_score": 11,
      "recommendation": "🔥 强烈推荐入场",
      "blue_ocean_index": 42.2,
      "dimensions": {
        "search_volume": 2,
        "search_volume_detail": "搜索结果422个",
        "avg_reviews": 2,
        "avg_reviews_detail": "TOP10平均评论71条",
        "seller_count": 2,
        "seller_count_detail": "TOP10卖家4家",
        "ozon_self": 1,
        "ozon_self_detail": "自营占比6.3%",
        "price_concentration": 2,
        "price_concentration_detail": "价格集中度0.60",
        "rating_variance": 1,
        "rating_variance_detail": "低评分占比28.0%",
        "rFBS_fitness": 1,
        "rFBS_fitness_detail": "标签: 蓝海, 旺季10-2月, 轻小件, 需提前备货"
      },
      "metrics": {
        "total_search_results": 422,
        "avg_price": 2170,
        "avg_reviews": 47,
        "avg_rating": 4.36,
        "unique_sellers": 9,
        "ozon_self_ratio": 0.0635,
        "price_concentration": 0.5986,
        "low_rating_ratio": 0.2801,
        "top10_avg_reviews": 71,
        "top10_avg_rating": 4.17,
        "top10_seller_count": 4,
        "price_min": 302,
        "price_max": 3972
      }
    },
    {
      "category": "车载夏季-冰丝方向盘套",
      "keyword_ru": "чехол на руль ледяной",
      "keyword_en": "ice silk steering wheel cover",
      "tags": [
        "季节性",
        "旺季5-8月",
        "轻小件",
        "清凉经济"
      ],
      "total_score": 11,
      "recommendation": "🔥 强烈推荐入场",
      "blue_ocean_index": 45.7,
      "dimensions": {
        "search_volume": 2,
        "search_volume_detail": "搜索结果457个",
        "avg_reviews": 2,
        "avg_reviews_detail": "TOP10平均评论96条",
        "seller_count": 2,
        "seller_count_detail": "TOP10卖家4家",
        "ozon_self": 1,
        "ozon_self_detail": "自营占比2.1%",
        "price_concentration": 2,
        "price_concentration_detail": "价格集中度0.58",
        "rating_variance": 1,
        "rating_variance_detail": "低评分占比20.7%",
        "rFBS_fitness": 1,
        "rFBS_fitness_detail": "标签: 季节性, 旺季5-8月, 轻小件, 清凉经济"
      },
      "metrics": {
        "total_search_results": 457,
        "avg_price": 1441,
        "avg_reviews": 121,
        "avg_rating": 4.61,
        "unique_sellers": 9,
        "ozon_self_ratio": 0.0205,
        "price_concentration": 0.5825,
        "low_rating_ratio": 0.2071,
        "top10_avg_reviews": 96,
        "top10_avg_rating": 4.59,
        "top10_seller_count": 4,
        "price_min": 359,
        "price_max": 3308
      }
    },
    {
      "category": "智能穿戴-健身手环",
      "keyword_ru": "умный браслет фитнес",
      "keyword_en": "fitness smart bracelet",
      "tags": [
        "蓝海",
        "全年品",
        "轻小件",
        "供给缺口>45%"
      ],
      "total_score": 11,
      "recommendation": "🔥 强烈推荐入场",
      "blue_ocean_index": 10.5,
      "dimensions": {
        "search_volume": 2,
        "search_volume_detail": "搜索结果147个",
        "avg_reviews": 2,
        "avg_reviews_detail": "TOP10平均评论82条",
        "seller_count": 2,
        "seller_count_detail": "TOP10卖家5家",
        "ozon_self": 1,
        "ozon_self_detail": "自营占比0.2%",
        "price_concentration": 2,
        "price_concentration_detail": "价格集中度0.57",
        "rating_variance": 1,
        "rating_variance_detail": "低评分占比28.3%",
        "rFBS_fitness": 1,
        "rFBS_fitness_detail": "标签: 蓝海, 全年品, 轻小件, 供给缺口>45%"
      },
      "metrics": {
        "total_search_results": 147,
        "avg_price": 827,
        "avg_reviews": 146,
        "avg_rating": 4.67,
        "unique_sellers": 13,
        "ozon_self_ratio": 0.0017,
        "price_concentration": 0.5728,
        "low_rating_ratio": 0.2831,
        "top10_avg_reviews": 82,
        "top10_avg_rating": 4.53,
        "top10_seller_count": 5,
        "price_min": 116,
        "price_max": 2306
      }
    },
    {
      "category": "智能穿戴-儿童定位手表",
      "keyword_ru": "часы детские с GPS трекером",
      "keyword_en": "kids GPS tracker watch",
      "tags": [
        "蓝海",
        "全年品",
        "轻小件",
        "母婴安全需求"
      ],
      "total_score": 11,
      "recommendation": "🔥 强烈推荐入场",
      "blue_ocean_index": 40.57,
      "dimensions": {
        "search_volume": 2,
        "search_volume_detail": "搜索结果568个",
        "avg_reviews": 2,
        "avg_reviews_detail": "TOP10平均评论98条",
        "seller_count": 2,
        "seller_count_detail": "TOP10卖家9家",
        "ozon_self": 1,
        "ozon_self_detail": "自营占比7.3%",
        "price_concentration": 2,
        "price_concentration_detail": "价格集中度0.45",
        "rating_variance": 1,
        "rating_variance_detail": "低评分占比25.9%",
        "rFBS_fitness": 1,
        "rFBS_fitness_detail": "标签: 蓝海, 全年品, 轻小件, 母婴安全需求"
      },
      "metrics": {
        "total_search_results": 568,
        "avg_price": 642,
        "avg_reviews": 82,
        "avg_rating": 4.62,
        "unique_sellers": 13,
        "ozon_self_ratio": 0.0734,
        "price_concentration": 0.4547,
        "low_rating_ratio": 0.2593,
        "top10_avg_reviews": 98,
        "top10_avg_rating": 4.6,
        "top10_seller_count": 9,
        "price_min": 118,
        "price_max": 2083
      }
    },
    {
      "category": "园艺智能-植物生长灯",
      "keyword_ru": "светильник для растений LED",
      "keyword_en": "LED plant grow light",
      "tags": [
        "蓝海",
        "旺季2-4月(备货)",
        "轻小件",
        "智能家居延伸"
      ],
      "total_score": 11,
      "recommendation": "🔥 强烈推荐入场",
      "blue_ocean_index": 19.73,
      "dimensions": {
        "search_volume": 2,
        "search_volume_detail": "搜索结果296个",
        "avg_reviews": 2,
        "avg_reviews_detail": "TOP10平均评论97条",
        "seller_count": 2,
        "seller_count_detail": "TOP10卖家9家",
        "ozon_self": 1,
        "ozon_self_detail": "自营占比4.9%",
        "price_concentration": 2,
        "price_concentration_detail": "价格集中度0.50",
        "rating_variance": 1,
        "rating_variance_detail": "低评分占比23.3%",
        "rFBS_fitness": 1,
        "rFBS_fitness_detail": "标签: 蓝海, 旺季2-4月(备货), 轻小件, 智能家居延伸"
      },
      "metrics": {
        "total_search_results": 296,
        "avg_price": 614,
        "avg_reviews": 104,
        "avg_rating": 4.66,
        "unique_sellers": 14,
        "ozon_self_ratio": 0.0494,
        "price_concentration": 0.5032,
        "low_rating_ratio": 0.2326,
        "top10_avg_reviews": 97,
        "top10_avg_rating": 4.57,
        "top10_seller_count": 9,
        "price_min": 249,
        "price_max": 1641
      }
    },
    {
      "category": "园艺装饰-太阳能户外灯",
      "keyword_ru": "фонарь солнечный для сада",
      "keyword_en": "solar garden lantern",
      "tags": [
        "刚需",
        "旺季5-9月",
        "轻小件",
        "达恰装饰"
      ],
      "total_score": 11,
      "recommendation": "🔥 强烈推荐入场",
      "blue_ocean_index": 62.33,
      "dimensions": {
        "search_volume": 2,
        "search_volume_detail": "搜索结果748个",
        "avg_reviews": 2,
        "avg_reviews_detail": "TOP10平均评论77条",
        "seller_count": 2,
        "seller_count_detail": "TOP10卖家5家",
        "ozon_self": 1,
        "ozon_self_detail": "自营占比5.0%",
        "price_concentration": 2,
        "price_concentration_detail": "价格集中度0.50",
        "rating_variance": 1,
        "rating_variance_detail": "低评分占比24.6%",
        "rFBS_fitness": 1,
        "rFBS_fitness_detail": "标签: 刚需, 旺季5-9月, 轻小件, 达恰装饰"
      },
      "metrics": {
        "total_search_results": 748,
        "avg_price": 525,
        "avg_reviews": 45,
        "avg_rating": 4.52,
        "unique_sellers": 11,
        "ozon_self_ratio": 0.0503,
        "price_concentration": 0.4968,
        "low_rating_ratio": 0.2455,
        "top10_avg_reviews": 77,
        "top10_avg_rating": 4.47,
        "top10_seller_count": 5,
        "price_min": 172,
        "price_max": 2430
      }
    },
    {
      "category": "户外休闲-便携吊床",
      "keyword_ru": "гамак портативный",
      "keyword_en": "portable hammock",
      "tags": [
        "季节性",
        "旺季6-8月",
        "轻小件",
        "度假季"
      ],
      "total_score": 11,
      "recommendation": "🔥 强烈推荐入场",
      "blue_ocean_index": 25.0,
      "dimensions": {
        "search_volume": 2,
        "search_volume_detail": "搜索结果175个",
        "avg_reviews": 2,
        "avg_reviews_detail": "TOP10平均评论34条",
        "seller_count": 2,
        "seller_count_detail": "TOP10卖家5家",
        "ozon_self": 1,
        "ozon_self_detail": "自营占比6.7%",
        "price_concentration": 2,
        "price_concentration_detail": "价格集中度0.46",
        "rating_variance": 1,
        "rating_variance_detail": "低评分占比27.2%",
        "rFBS_fitness": 1,
        "rFBS_fitness_detail": "标签: 季节性, 旺季6-8月, 轻小件, 度假季"
      },
      "metrics": {
        "total_search_results": 175,
        "avg_price": 712,
        "avg_reviews": 129,
        "avg_rating": 4.73,
        "unique_sellers": 6,
        "ozon_self_ratio": 0.067,
        "price_concentration": 0.4613,
        "low_rating_ratio": 0.2724,
        "top10_avg_reviews": 34,
        "top10_avg_rating": 4.58,
        "top10_seller_count": 5,
        "price_min": 225,
        "price_max": 2312
      }
    },
    {
      "category": "益智玩具-磁力片",
      "keyword_ru": "магнитные блоки для детей",
      "keyword_en": "magnetic building blocks",
      "tags": [
        "蓝海",
        "全年品",
        "轻小件",
        "低佣金5-8%",
        "高复购"
      ],
      "total_score": 11,
      "recommendation": "🔥 强烈推荐入场",
      "blue_ocean_index": 32.92,
      "dimensions": {
        "search_volume": 2,
        "search_volume_detail": "搜索结果395个",
        "avg_reviews": 2,
        "avg_reviews_detail": "TOP10平均评论86条",
        "seller_count": 2,
        "seller_count_detail": "TOP10卖家3家",
        "ozon_self": 1,
        "ozon_self_detail": "自营占比3.8%",
        "price_concentration": 2,
        "price_concentration_detail": "价格集中度0.53",
        "rating_variance": 1,
        "rating_variance_detail": "低评分占比27.3%",
        "rFBS_fitness": 1,
        "rFBS_fitness_detail": "标签: 蓝海, 全年品, 轻小件, 低佣金5-8%, 高复购"
      },
      "metrics": {
        "total_search_results": 395,
        "avg_price": 495,
        "avg_reviews": 146,
        "avg_rating": 4.43,
        "unique_sellers": 11,
        "ozon_self_ratio": 0.038,
        "price_concentration": 0.5307,
        "low_rating_ratio": 0.273,
        "top10_avg_reviews": 86,
        "top10_avg_rating": 4.27,
        "top10_seller_count": 3,
        "price_min": 113,
        "price_max": 1574
      }
    },
    {
      "category": "益智玩具-科学实验套装",
      "keyword_ru": "набор научных экспериментов для детей",
      "keyword_en": "kids science experiment kit",
      "tags": [
        "探索",
        "全年品",
        "轻小件",
        "教育蓝海"
      ],
      "total_score": 11,
      "recommendation": "🔥 强烈推荐入场",
      "blue_ocean_index": 29.5,
      "dimensions": {
        "search_volume": 2,
        "search_volume_detail": "搜索结果118个",
        "avg_reviews": 2,
        "avg_reviews_detail": "TOP10平均评论18条",
        "seller_count": 2,
        "seller_count_detail": "TOP10卖家3家",
        "ozon_self": 1,
        "ozon_self_detail": "自营占比4.8%",
        "price_concentration": 2,
        "price_concentration_detail": "价格集中度0.42",
        "rating_variance": 1,
        "rating_variance_detail": "低评分占比24.7%",
        "rFBS_fitness": 1,
        "rFBS_fitness_detail": "标签: 探索, 全年品, 轻小件, 教育蓝海"
      },
      "metrics": {
        "total_search_results": 118,
        "avg_price": 790,
        "avg_reviews": 24,
        "avg_rating": 4.58,
        "unique_sellers": 3,
        "ozon_self_ratio": 0.048,
        "price_concentration": 0.4183,
        "low_rating_ratio": 0.2468,
        "top10_avg_reviews": 18,
        "top10_avg_rating": 4.53,
        "top10_seller_count": 3,
        "price_min": 145,
        "price_max": 1900
      }
    },
    {
      "category": "夏季刚需-防晒渔夫帽",
      "keyword_ru": "солнцезащитная шапка рыбака",
      "keyword_en": "sun protection fishing hat",
      "tags": [
        "季节性",
        "旺季5-8月",
        "轻小件",
        "户外钓鱼季"
      ],
      "total_score": 11,
      "recommendation": "🔥 强烈推荐入场",
      "blue_ocean_index": 58.22,
      "dimensions": {
        "search_volume": 2,
        "search_volume_detail": "搜索结果524个",
        "avg_reviews": 2,
        "avg_reviews_detail": "TOP10平均评论76条",
        "seller_count": 2,
        "seller_count_detail": "TOP10卖家6家",
        "ozon_self": 1,
        "ozon_self_detail": "自营占比6.4%",
        "price_concentration": 2,
        "price_concentration_detail": "价格集中度0.45",
        "rating_variance": 1,
        "rating_variance_detail": "低评分占比21.5%",
        "rFBS_fitness": 1,
        "rFBS_fitness_detail": "标签: 季节性, 旺季5-8月, 轻小件, 户外钓鱼季"
      },
      "metrics": {
        "total_search_results": 524,
        "avg_price": 600,
        "avg_reviews": 80,
        "avg_rating": 4.39,
        "unique_sellers": 8,
        "ozon_self_ratio": 0.0641,
        "price_concentration": 0.4535,
        "low_rating_ratio": 0.2146,
        "top10_avg_reviews": 76,
        "top10_avg_rating": 4.26,
        "top10_seller_count": 6,
        "price_min": 155,
        "price_max": 2001
      }
    },
    {
      "category": "宠物智能-猫喂食器",
      "keyword_ru": "автоматическая кормушка для кошек",
      "keyword_en": "automatic cat feeder",
      "tags": [
        "蓝海",
        "全年品",
        "轻小件",
        "高增长"
      ],
      "total_score": 10.5,
      "recommendation": "🔥 强烈推荐入场",
      "blue_ocean_index": 31.0,
      "dimensions": {
        "search_volume": 2,
        "search_volume_detail": "搜索结果341个",
        "avg_reviews": 2,
        "avg_reviews_detail": "TOP10平均评论85条",
        "seller_count": 2,
        "seller_count_detail": "TOP10卖家9家",
        "ozon_self": 1,
        "ozon_self_detail": "自营占比7.7%",
        "price_concentration": 2,
        "price_concentration_detail": "价格集中度0.45",
        "rating_variance": 0.5,
        "rating_variance_detail": "低评分占比18.8%",
        "rFBS_fitness": 1,
        "rFBS_fitness_detail": "标签: 蓝海, 全年品, 轻小件, 高增长"
      },
      "metrics": {
        "total_search_results": 341,
        "avg_price": 822,
        "avg_reviews": 27,
        "avg_rating": 4.69,
        "unique_sellers": 10,
        "ozon_self_ratio": 0.0769,
        "price_concentration": 0.4479,
        "low_rating_ratio": 0.1881,
        "top10_avg_reviews": 85,
        "top10_avg_rating": 4.5,
        "top10_seller_count": 9,
        "price_min": 148,
        "price_max": 2402
      }
    },
    {
      "category": "宠物智能-小型犬喂食器",
      "keyword_ru": "автокормушка для собак малых пород",
      "keyword_en": "small dog automatic feeder",
      "tags": [
        "蓝海",
        "全年品",
        "轻小件",
        "高增长"
      ],
      "total_score": 10.5,
      "recommendation": "🔥 强烈推荐入场",
      "blue_ocean_index": 13.62,
      "dimensions": {
        "search_volume": 2,
        "search_volume_detail": "搜索结果218个",
        "avg_reviews": 2,
        "avg_reviews_detail": "TOP10平均评论84条",
        "seller_count": 2,
        "seller_count_detail": "TOP10卖家4家",
        "ozon_self": 1,
        "ozon_self_detail": "自营占比0.4%",
        "price_concentration": 2,
        "price_concentration_detail": "价格集中度0.44",
        "rating_variance": 0.5,
        "rating_variance_detail": "低评分占比19.8%",
        "rFBS_fitness": 1,
        "rFBS_fitness_detail": "标签: 蓝海, 全年品, 轻小件, 高增长"
      },
      "metrics": {
        "total_search_results": 218,
        "avg_price": 995,
        "avg_reviews": 75,
        "avg_rating": 4.43,
        "unique_sellers": 15,
        "ozon_self_ratio": 0.004,
        "price_concentration": 0.4425,
        "low_rating_ratio": 0.1975,
        "top10_avg_reviews": 84,
        "top10_avg_rating": 4.25,
        "top10_seller_count": 4,
        "price_min": 210,
        "price_max": 1732
      }
    },
    {
      "category": "宠物玩具-互动类",
      "keyword_ru": "игрушка для кошек интерактивная",
      "keyword_en": "interactive cat toy",
      "tags": [
        "蓝海",
        "复购率高",
        "轻小件",
        "低退货"
      ],
      "total_score": 10.5,
      "recommendation": "🔥 强烈推荐入场",
      "blue_ocean_index": 77.56,
      "dimensions": {
        "search_volume": 2,
        "search_volume_detail": "搜索结果698个",
        "avg_reviews": 2,
        "avg_reviews_detail": "TOP10平均评论73条",
        "seller_count": 2,
        "seller_count_detail": "TOP10卖家8家",
        "ozon_self": 1,
        "ozon_self_detail": "自营占比1.7%",
        "price_concentration": 2,
        "price_concentration_detail": "价格集中度0.43",
        "rating_variance": 0.5,
        "rating_variance_detail": "低评分占比19.7%",
        "rFBS_fitness": 1,
        "rFBS_fitness_detail": "标签: 蓝海, 复购率高, 轻小件, 低退货"
      },
      "metrics": {
        "total_search_results": 698,
        "avg_price": 389,
        "avg_reviews": 114,
        "avg_rating": 4.79,
        "unique_sellers": 8,
        "ozon_self_ratio": 0.0174,
        "price_concentration": 0.4295,
        "low_rating_ratio": 0.1965,
        "top10_avg_reviews": 73,
        "top10_avg_rating": 4.77,
        "top10_seller_count": 8,
        "price_min": 182,
        "price_max": 1602
      }
    },
    {
      "category": "车载配件-无线充电手机支架",
      "keyword_ru": "держатель для телефона в авто с зарядкой",
      "keyword_en": "car phone holder wireless charging",
      "tags": [
        "蓝海",
        "全年品",
        "轻小件",
        "高增长"
      ],
      "total_score": 10.5,
      "recommendation": "🔥 强烈推荐入场",
      "blue_ocean_index": 45.15,
      "dimensions": {
        "search_volume": 2,
        "search_volume_detail": "搜索结果587个",
        "avg_reviews": 2,
        "avg_reviews_detail": "TOP10平均评论18条",
        "seller_count": 2,
        "seller_count_detail": "TOP10卖家9家",
        "ozon_self": 1,
        "ozon_self_detail": "自营占比7.8%",
        "price_concentration": 2,
        "price_concentration_detail": "价格集中度0.50",
        "rating_variance": 0.5,
        "rating_variance_detail": "低评分占比20.0%",
        "rFBS_fitness": 1,
        "rFBS_fitness_detail": "标签: 蓝海, 全年品, 轻小件, 高增长"
      },
      "metrics": {
        "total_search_results": 587,
        "avg_price": 881,
        "avg_reviews": 57,
        "avg_rating": 4.51,
        "unique_sellers": 12,
        "ozon_self_ratio": 0.0776,
        "price_concentration": 0.4959,
        "low_rating_ratio": 0.1996,
        "top10_avg_reviews": 18,
        "top10_avg_rating": 4.51,
        "top10_seller_count": 9,
        "price_min": 477,
        "price_max": 4844
      }
    },
    {
      "category": "智能穿戴-健康智能戒指",
      "keyword_ru": "кольцо умное для здоровья",
      "keyword_en": "smart health ring",
      "tags": [
        "探索",
        "全年品",
        "轻小件",
        "新兴品类"
      ],
      "total_score": 10.5,
      "recommendation": "🔥 强烈推荐入场",
      "blue_ocean_index": 16.29,
      "dimensions": {
        "search_volume": 2,
        "search_volume_detail": "搜索结果114个",
        "avg_reviews": 2,
        "avg_reviews_detail": "TOP10平均评论18条",
        "seller_count": 2,
        "seller_count_detail": "TOP10卖家3家",
        "ozon_self": 1,
        "ozon_self_detail": "自营占比4.5%",
        "price_concentration": 2,
        "price_concentration_detail": "价格集中度0.45",
        "rating_variance": 0.5,
        "rating_variance_detail": "低评分占比15.5%",
        "rFBS_fitness": 1,
        "rFBS_fitness_detail": "标签: 探索, 全年品, 轻小件, 新兴品类"
      },
      "metrics": {
        "total_search_results": 114,
        "avg_price": 839,
        "avg_reviews": 51,
        "avg_rating": 4.46,
        "unique_sellers": 6,
        "ozon_self_ratio": 0.0453,
        "price_concentration": 0.4469,
        "low_rating_ratio": 0.1549,
        "top10_avg_reviews": 18,
        "top10_avg_rating": 4.31,
        "top10_seller_count": 3,
        "price_min": 163,
        "price_max": 2511
      }
    },
    {
      "category": "节日装饰-新年LED灯串",
      "keyword_ru": "гирлянда новогодняя LED",
      "keyword_en": "LED Christmas string lights",
      "tags": [
        "季节性",
        "旺季11-12月",
        "轻小件",
        "全年利润30-40%来自此阶段"
      ],
      "total_score": 10.5,
      "recommendation": "🔥 强烈推荐入场",
      "blue_ocean_index": 90.86,
      "dimensions": {
        "search_volume": 2,
        "search_volume_detail": "搜索结果636个",
        "avg_reviews": 2,
        "avg_reviews_detail": "TOP10平均评论58条",
        "seller_count": 2,
        "seller_count_detail": "TOP10卖家6家",
        "ozon_self": 1,
        "ozon_self_detail": "自营占比4.5%",
        "price_concentration": 2,
        "price_concentration_detail": "价格集中度0.56",
        "rating_variance": 0.5,
        "rating_variance_detail": "低评分占比16.9%",
        "rFBS_fitness": 1,
        "rFBS_fitness_detail": "标签: 季节性, 旺季11-12月, 轻小件, 全年利润30-40%来自此阶段"
      },
      "metrics": {
        "total_search_results": 636,
        "avg_price": 341,
        "avg_reviews": 120,
        "avg_rating": 4.56,
        "unique_sellers": 6,
        "ozon_self_ratio": 0.0448,
        "price_concentration": 0.5565,
        "low_rating_ratio": 0.1693,
        "top10_avg_reviews": 58,
        "top10_avg_rating": 4.43,
        "top10_seller_count": 6,
        "price_min": 119,
        "price_max": 2384
      }
    },
    {
      "category": "宠物清洁-猫砂盆支架",
      "keyword_ru": "держатель для туалета кошки",
      "keyword_en": "cat litter box holder",
      "tags": [
        "刚需",
        "全年品",
        "轻小件",
        "低退货"
      ],
      "total_score": 10,
      "recommendation": "🔥 强烈推荐入场",
      "blue_ocean_index": 114.29,
      "dimensions": {
        "search_volume": 2,
        "search_volume_detail": "搜索结果800个",
        "avg_reviews": 2,
        "avg_reviews_detail": "TOP10平均评论18条",
        "seller_count": 1,
        "seller_count_detail": "TOP10卖家10家",
        "ozon_self": 1,
        "ozon_self_detail": "自营占比3.8%",
        "price_concentration": 2,
        "price_concentration_detail": "价格集中度0.49",
        "rating_variance": 1,
        "rating_variance_detail": "低评分占比23.2%",
        "rFBS_fitness": 1,
        "rFBS_fitness_detail": "标签: 刚需, 全年品, 轻小件, 低退货"
      },
      "metrics": {
        "total_search_results": 800,
        "avg_price": 723,
        "avg_reviews": 83,
        "avg_rating": 4.48,
        "unique_sellers": 6,
        "ozon_self_ratio": 0.0379,
        "price_concentration": 0.4921,
        "low_rating_ratio": 0.2315,
        "top10_avg_reviews": 18,
        "top10_avg_rating": 4.43,
        "top10_seller_count": 10,
        "price_min": 141,
        "price_max": 1529
      }
    },
    {
      "category": "浴室收纳-折叠置物架",
      "keyword_ru": "полка складная для ванной",
      "keyword_en": "foldable bathroom shelf",
      "tags": [
        "刚需",
        "全年品",
        "中等体积",
        "高复购"
      ],
      "total_score": 10.0,
      "recommendation": "🔥 强烈推荐入场",
      "blue_ocean_index": 55.44,
      "dimensions": {
        "search_volume": 2,
        "search_volume_detail": "搜索结果499个",
        "avg_reviews": 2,
        "avg_reviews_detail": "TOP10平均评论40条",
        "seller_count": 2,
        "seller_count_detail": "TOP10卖家8家",
        "ozon_self": 1,
        "ozon_self_detail": "自营占比4.0%",
        "price_concentration": 2,
        "price_concentration_detail": "价格集中度0.47",
        "rating_variance": 0.5,
        "rating_variance_detail": "低评分占比18.0%",
        "rFBS_fitness": 0.5,
        "rFBS_fitness_detail": "标签: 刚需, 全年品, 中等体积, 高复购"
      },
      "metrics": {
        "total_search_results": 499,
        "avg_price": 460,
        "avg_reviews": 87,
        "avg_rating": 4.44,
        "unique_sellers": 8,
        "ozon_self_ratio": 0.04,
        "price_concentration": 0.4675,
        "low_rating_ratio": 0.1801,
        "top10_avg_reviews": 40,
        "top10_avg_rating": 4.35,
        "top10_seller_count": 8,
        "price_min": 231,
        "price_max": 2076
      }
    },
    {
      "category": "厨房收纳-迷你沥水架",
      "keyword_ru": "сушилка для посуды компактная",
      "keyword_en": "compact dish drying rack",
      "tags": [
        "刚需",
        "全年品",
        "轻小件"
      ],
      "total_score": 10,
      "recommendation": "🔥 强烈推荐入场",
      "blue_ocean_index": 20.11,
      "dimensions": {
        "search_volume": 2,
        "search_volume_detail": "搜索结果181个",
        "avg_reviews": 2,
        "avg_reviews_detail": "TOP10平均评论62条",
        "seller_count": 2,
        "seller_count_detail": "TOP10卖家5家",
        "ozon_self": 1,
        "ozon_self_detail": "自营占比7.0%",
        "price_concentration": 1,
        "price_concentration_detail": "价格集中度0.35",
        "rating_variance": 1,
        "rating_variance_detail": "低评分占比26.2%",
        "rFBS_fitness": 1,
        "rFBS_fitness_detail": "标签: 刚需, 全年品, 轻小件"
      },
      "metrics": {
        "total_search_results": 181,
        "avg_price": 877,
        "avg_reviews": 73,
        "avg_rating": 4.55,
        "unique_sellers": 8,
        "ozon_self_ratio": 0.0698,
        "price_concentration": 0.3517,
        "low_rating_ratio": 0.2616,
        "top10_avg_reviews": 62,
        "top10_avg_rating": 4.36,
        "top10_seller_count": 5,
        "price_min": 178,
        "price_max": 2024
      }
    },
    {
      "category": "家居智能-自动皂液器",
      "keyword_ru": "дозатор для мыла автоматический",
      "keyword_en": "automatic soap dispenser",
      "tags": [
        "蓝海",
        "全年品",
        "轻小件",
        "智能家居延伸"
      ],
      "total_score": 10,
      "recommendation": "🔥 强烈推荐入场",
      "blue_ocean_index": 54.25,
      "dimensions": {
        "search_volume": 2,
        "search_volume_detail": "搜索结果434个",
        "avg_reviews": 2,
        "avg_reviews_detail": "TOP10平均评论43条",
        "seller_count": 1,
        "seller_count_detail": "TOP10卖家10家",
        "ozon_self": 1,
        "ozon_self_detail": "自营占比7.8%",
        "price_concentration": 2,
        "price_concentration_detail": "价格集中度0.54",
        "rating_variance": 1,
        "rating_variance_detail": "低评分占比21.9%",
        "rFBS_fitness": 1,
        "rFBS_fitness_detail": "标签: 蓝海, 全年品, 轻小件, 智能家居延伸"
      },
      "metrics": {
        "total_search_results": 434,
        "avg_price": 779,
        "avg_reviews": 148,
        "avg_rating": 4.46,
        "unique_sellers": 7,
        "ozon_self_ratio": 0.078,
        "price_concentration": 0.5385,
        "low_rating_ratio": 0.2187,
        "top10_avg_reviews": 43,
        "top10_avg_rating": 4.28,
        "top10_seller_count": 10,
        "price_min": 211,
        "price_max": 1673
      }
    },
    {
      "category": "车载收纳-后备箱整理箱",
      "keyword_ru": "органайзер для багажника авто",
      "keyword_en": "car trunk organizer",
      "tags": [
        "刚需",
        "全年品",
        "中等体积",
        "高增长"
      ],
      "total_score": 10.0,
      "recommendation": "🔥 强烈推荐入场",
      "blue_ocean_index": 21.81,
      "dimensions": {
        "search_volume": 2,
        "search_volume_detail": "搜索结果349个",
        "avg_reviews": 2,
        "avg_reviews_detail": "TOP10平均评论82条",
        "seller_count": 2,
        "seller_count_detail": "TOP10卖家7家",
        "ozon_self": 1,
        "ozon_self_detail": "自营占比0.2%",
        "price_concentration": 2,
        "price_concentration_detail": "价格集中度0.49",
        "rating_variance": 0.5,
        "rating_variance_detail": "低评分占比16.9%",
        "rFBS_fitness": 0.5,
        "rFBS_fitness_detail": "标签: 刚需, 全年品, 中等体积, 高增长"
      },
      "metrics": {
        "total_search_results": 349,
        "avg_price": 1861,
        "avg_reviews": 124,
        "avg_rating": 4.35,
        "unique_sellers": 15,
        "ozon_self_ratio": 0.0017,
        "price_concentration": 0.491,
        "low_rating_ratio": 0.1689,
        "top10_avg_reviews": 82,
        "top10_avg_rating": 4.25,
        "top10_seller_count": 7,
        "price_min": 387,
        "price_max": 4058
      }
    },
    {
      "category": "园艺工具-迷你套装",
      "keyword_ru": "набор инструментов для сада мини",
      "keyword_en": "mini garden tools set",
      "tags": [
        "蓝海",
        "旺季4-9月",
        "轻小件",
        "达恰刚需"
      ],
      "total_score": 10,
      "recommendation": "🔥 强烈推荐入场",
      "blue_ocean_index": 80.89,
      "dimensions": {
        "search_volume": 2,
        "search_volume_detail": "搜索结果728个",
        "avg_reviews": 2,
        "avg_reviews_detail": "TOP10平均评论65条",
        "seller_count": 2,
        "seller_count_detail": "TOP10卖家8家",
        "ozon_self": 1,
        "ozon_self_detail": "自营占比4.0%",
        "price_concentration": 1,
        "price_concentration_detail": "价格集中度0.36",
        "rating_variance": 1,
        "rating_variance_detail": "低评分占比22.6%",
        "rFBS_fitness": 1,
        "rFBS_fitness_detail": "标签: 蓝海, 旺季4-9月, 轻小件, 达恰刚需"
      },
      "metrics": {
        "total_search_results": 728,
        "avg_price": 565,
        "avg_reviews": 118,
        "avg_rating": 4.3,
        "unique_sellers": 8,
        "ozon_self_ratio": 0.04,
        "price_concentration": 0.3609,
        "low_rating_ratio": 0.2258,
        "top10_avg_reviews": 65,
        "top10_avg_rating": 4.19,
        "top10_seller_count": 8,
        "price_min": 117,
        "price_max": 2199
      }
    },
    {
      "category": "教育用品-书法套装",
      "keyword_ru": "набор для каллиграфии",
      "keyword_en": "calligraphy set",
      "tags": [
        "蓝海",
        "全年品",
        "轻小件",
        "政策红利"
      ],
      "total_score": 10,
      "recommendation": "🔥 强烈推荐入场",
      "blue_ocean_index": 35.5,
      "dimensions": {
        "search_volume": 2,
        "search_volume_detail": "搜索结果355个",
        "avg_reviews": 2,
        "avg_reviews_detail": "TOP10平均评论68条",
        "seller_count": 2,
        "seller_count_detail": "TOP10卖家4家",
        "ozon_self": 1,
        "ozon_self_detail": "自营占比1.5%",
        "price_concentration": 1,
        "price_concentration_detail": "价格集中度0.35",
        "rating_variance": 1,
        "rating_variance_detail": "低评分占比20.9%",
        "rFBS_fitness": 1,
        "rFBS_fitness_detail": "标签: 蓝海, 全年品, 轻小件, 政策红利"
      },
      "metrics": {
        "total_search_results": 355,
        "avg_price": 485,
        "avg_reviews": 52,
        "avg_rating": 4.44,
        "unique_sellers": 9,
        "ozon_self_ratio": 0.0151,
        "price_concentration": 0.3525,
        "low_rating_ratio": 0.2094,
        "top10_avg_reviews": 68,
        "top10_avg_rating": 4.25,
        "top10_seller_count": 4,
        "price_min": 162,
        "price_max": 1595
      }
    },
    {
      "category": "益智玩具-木质拼装",
      "keyword_ru": "конструктор деревянный",
      "keyword_en": "wooden building blocks",
      "tags": [
        "探索",
        "全年品",
        "轻小件",
        "低佣金",
        "环保趋势"
      ],
      "total_score": 10,
      "recommendation": "🔥 强烈推荐入场",
      "blue_ocean_index": 37.43,
      "dimensions": {
        "search_volume": 2,
        "search_volume_detail": "搜索结果262个",
        "avg_reviews": 2,
        "avg_reviews_detail": "TOP10平均评论7条",
        "seller_count": 2,
        "seller_count_detail": "TOP10卖家5家",
        "ozon_self": 1,
        "ozon_self_detail": "自营占比4.5%",
        "price_concentration": 1,
        "price_concentration_detail": "价格集中度0.37",
        "rating_variance": 1,
        "rating_variance_detail": "低评分占比22.2%",
        "rFBS_fitness": 1,
        "rFBS_fitness_detail": "标签: 探索, 全年品, 轻小件, 低佣金, 环保趋势"
      },
      "metrics": {
        "total_search_results": 262,
        "avg_price": 564,
        "avg_reviews": 51,
        "avg_rating": 4.27,
        "unique_sellers": 6,
        "ozon_self_ratio": 0.0449,
        "price_concentration": 0.372,
        "low_rating_ratio": 0.2219,
        "top10_avg_reviews": 7,
        "top10_avg_rating": 4.07,
        "top10_seller_count": 5,
        "price_min": 224,
        "price_max": 1822
      }
    },
    {
      "category": "夏季刚需-便携USB小风扇",
      "keyword_ru": "веер USB портативный",
      "keyword_en": "portable USB fan",
      "tags": [
        "季节性",
        "旺季6-8月",
        "轻小件",
        "当前窗口",
        "成本¥15卖¥80-120"
      ],
      "total_score": 10,
      "recommendation": "🔥 强烈推荐入场",
      "blue_ocean_index": 41.0,
      "dimensions": {
        "search_volume": 2,
        "search_volume_detail": "搜索结果246个",
        "avg_reviews": 2,
        "avg_reviews_detail": "TOP10平均评论13条",
        "seller_count": 1,
        "seller_count_detail": "TOP10卖家10家",
        "ozon_self": 1,
        "ozon_self_detail": "自营占比2.5%",
        "price_concentration": 2,
        "price_concentration_detail": "价格集中度0.58",
        "rating_variance": 1,
        "rating_variance_detail": "低评分占比30.0%",
        "rFBS_fitness": 1,
        "rFBS_fitness_detail": "标签: 季节性, 旺季6-8月, 轻小件, 当前窗口, 成本¥15卖¥80-120"
      },
      "metrics": {
        "total_search_results": 246,
        "avg_price": 811,
        "avg_reviews": 76,
        "avg_rating": 4.31,
        "unique_sellers": 5,
        "ozon_self_ratio": 0.025,
        "price_concentration": 0.5775,
        "low_rating_ratio": 0.3,
        "top10_avg_reviews": 13,
        "top10_avg_rating": 4.17,
        "top10_seller_count": 10,
        "price_min": 209,
        "price_max": 2726
      }
    },
    {
      "category": "冬季保暖-加热手套",
      "keyword_ru": "перчатки с подогревом USB",
      "keyword_en": "USB heated gloves",
      "tags": [
        "季节性",
        "旺季10-2月",
        "轻小件",
        "需提前备货"
      ],
      "total_score": 10,
      "recommendation": "🔥 强烈推荐入场",
      "blue_ocean_index": 45.08,
      "dimensions": {
        "search_volume": 2,
        "search_volume_detail": "搜索结果541个",
        "avg_reviews": 2,
        "avg_reviews_detail": "TOP10平均评论19条",
        "seller_count": 2,
        "seller_count_detail": "TOP10卖家6家",
        "ozon_self": 1,
        "ozon_self_detail": "自营占比0.4%",
        "price_concentration": 1,
        "price_concentration_detail": "价格集中度0.36",
        "rating_variance": 1,
        "rating_variance_detail": "低评分占比25.6%",
        "rFBS_fitness": 1,
        "rFBS_fitness_detail": "标签: 季节性, 旺季10-2月, 轻小件, 需提前备货"
      },
      "metrics": {
        "total_search_results": 541,
        "avg_price": 1614,
        "avg_reviews": 35,
        "avg_rating": 4.75,
        "unique_sellers": 11,
        "ozon_self_ratio": 0.0036,
        "price_concentration": 0.3604,
        "low_rating_ratio": 0.256,
        "top10_avg_reviews": 19,
        "top10_avg_rating": 4.6,
        "top10_seller_count": 6,
        "price_min": 386,
        "price_max": 3729
      }
    },
    {
      "category": "厨房工具-调料瓶/罐",
      "keyword_ru": "контейнеры для специй",
      "keyword_en": "spice containers",
      "tags": [
        "蓝海",
        "全年刚需",
        "轻小件",
        "高复购"
      ],
      "total_score": 9.5,
      "recommendation": "🔥 强烈推荐入场",
      "blue_ocean_index": 54.62,
      "dimensions": {
        "search_volume": 2,
        "search_volume_detail": "搜索结果710个",
        "avg_reviews": 2,
        "avg_reviews_detail": "TOP10平均评论23条",
        "seller_count": 1,
        "seller_count_detail": "TOP10卖家10家",
        "ozon_self": 1,
        "ozon_self_detail": "自营占比0.7%",
        "price_concentration": 2,
        "price_concentration_detail": "价格集中度0.58",
        "rating_variance": 0.5,
        "rating_variance_detail": "低评分占比18.4%",
        "rFBS_fitness": 1,
        "rFBS_fitness_detail": "标签: 蓝海, 全年刚需, 轻小件, 高复购"
      },
      "metrics": {
        "total_search_results": 710,
        "avg_price": 757,
        "avg_reviews": 26,
        "avg_rating": 4.59,
        "unique_sellers": 12,
        "ozon_self_ratio": 0.007,
        "price_concentration": 0.5792,
        "low_rating_ratio": 0.1836,
        "top10_avg_reviews": 23,
        "top10_avg_rating": 4.51,
        "top10_seller_count": 10,
        "price_min": 249,
        "price_max": 2251
      }
    },
    {
      "category": "园艺工具-修剪剪刀",
      "keyword_ru": "садовые ножницы",
      "keyword_en": "pruning shears",
      "tags": [
        "蓝海",
        "旺季5-9月",
        "轻小件",
        "达恰刚需"
      ],
      "total_score": 9.5,
      "recommendation": "🔥 强烈推荐入场",
      "blue_ocean_index": 55.83,
      "dimensions": {
        "search_volume": 2,
        "search_volume_detail": "搜索结果670个",
        "avg_reviews": 2,
        "avg_reviews_detail": "TOP10平均评论21条",
        "seller_count": 1,
        "seller_count_detail": "TOP10卖家10家",
        "ozon_self": 1,
        "ozon_self_detail": "自营占比7.4%",
        "price_concentration": 2,
        "price_concentration_detail": "价格集中度0.52",
        "rating_variance": 0.5,
        "rating_variance_detail": "低评分占比19.0%",
        "rFBS_fitness": 1,
        "rFBS_fitness_detail": "标签: 蓝海, 旺季5-9月, 轻小件, 达恰刚需"
      },
      "metrics": {
        "total_search_results": 670,
        "avg_price": 719,
        "avg_reviews": 15,
        "avg_rating": 4.51,
        "unique_sellers": 11,
        "ozon_self_ratio": 0.0742,
        "price_concentration": 0.5207,
        "low_rating_ratio": 0.1899,
        "top10_avg_reviews": 21,
        "top10_avg_rating": 4.5,
        "top10_seller_count": 10,
        "price_min": 103,
        "price_max": 1624
      }
    },
    {
      "category": "夏季刚需-驱蚊手环/便携驱蚊器",
      "keyword_ru": "репеллент от комаров портативный",
      "keyword_en": "portable mosquito repellent",
      "tags": [
        "季节性",
        "旺季6-8月",
        "轻小件",
        "当前窗口"
      ],
      "total_score": 9.5,
      "recommendation": "🔥 强烈推荐入场",
      "blue_ocean_index": 33.18,
      "dimensions": {
        "search_volume": 2,
        "search_volume_detail": "搜索结果365个",
        "avg_reviews": 2,
        "avg_reviews_detail": "TOP10平均评论87条",
        "seller_count": 2,
        "seller_count_detail": "TOP10卖家9家",
        "ozon_self": 1,
        "ozon_self_detail": "自营占比3.5%",
        "price_concentration": 1,
        "price_concentration_detail": "价格集中度0.37",
        "rating_variance": 0.5,
        "rating_variance_detail": "低评分占比16.0%",
        "rFBS_fitness": 1,
        "rFBS_fitness_detail": "标签: 季节性, 旺季6-8月, 轻小件, 当前窗口"
      },
      "metrics": {
        "total_search_results": 365,
        "avg_price": 523,
        "avg_reviews": 32,
        "avg_rating": 4.76,
        "unique_sellers": 10,
        "ozon_self_ratio": 0.0351,
        "price_concentration": 0.3652,
        "low_rating_ratio": 0.1597,
        "top10_avg_reviews": 87,
        "top10_avg_rating": 4.75,
        "top10_seller_count": 9,
        "price_min": 192,
        "price_max": 2884
      }
    },
    {
      "category": "冬季保暖-暖手宝",
      "keyword_ru": "портативный обогреватель для рук",
      "keyword_en": "portable hand warmer",
      "tags": [
        "季节性",
        "旺季10-2月",
        "轻小件",
        "需提前备货"
      ],
      "total_score": 9.5,
      "recommendation": "🔥 强烈推荐入场",
      "blue_ocean_index": 49.0,
      "dimensions": {
        "search_volume": 2,
        "search_volume_detail": "搜索结果588个",
        "avg_reviews": 2,
        "avg_reviews_detail": "TOP10平均评论99条",
        "seller_count": 2,
        "seller_count_detail": "TOP10卖家9家",
        "ozon_self": 1,
        "ozon_self_detail": "自营占比1.0%",
        "price_concentration": 1,
        "price_concentration_detail": "价格集中度0.39",
        "rating_variance": 0.5,
        "rating_variance_detail": "低评分占比17.0%",
        "rFBS_fitness": 1,
        "rFBS_fitness_detail": "标签: 季节性, 旺季10-2月, 轻小件, 需提前备货"
      },
      "metrics": {
        "total_search_results": 588,
        "avg_price": 1609,
        "avg_reviews": 115,
        "avg_rating": 4.61,
        "unique_sellers": 11,
        "ozon_self_ratio": 0.0097,
        "price_concentration": 0.3869,
        "low_rating_ratio": 0.1699,
        "top10_avg_reviews": 99,
        "top10_avg_rating": 4.53,
        "top10_seller_count": 9,
        "price_min": 481,
        "price_max": 4132
      }
    },
    {
      "category": "节日礼品-香薰蜡烛礼盒",
      "keyword_ru": "свеча ароматическая в подарке",
      "keyword_en": "scented candle gift set",
      "tags": [
        "季节性",
        "2月/3月/12月",
        "轻小件",
        "冲动消费高"
      ],
      "total_score": 9.5,
      "recommendation": "🔥 强烈推荐入场",
      "blue_ocean_index": 106.83,
      "dimensions": {
        "search_volume": 2,
        "search_volume_detail": "搜索结果641个",
        "avg_reviews": 2,
        "avg_reviews_detail": "TOP10平均评论21条",
        "seller_count": 1,
        "seller_count_detail": "TOP10卖家10家",
        "ozon_self": 1,
        "ozon_self_detail": "自营占比6.5%",
        "price_concentration": 2,
        "price_concentration_detail": "价格集中度0.51",
        "rating_variance": 0.5,
        "rating_variance_detail": "低评分占比19.4%",
        "rFBS_fitness": 1,
        "rFBS_fitness_detail": "标签: 季节性, 2月/3月/12月, 轻小件, 冲动消费高"
      },
      "metrics": {
        "total_search_results": 641,
        "avg_price": 972,
        "avg_reviews": 80,
        "avg_rating": 4.78,
        "unique_sellers": 5,
        "ozon_self_ratio": 0.0645,
        "price_concentration": 0.5075,
        "low_rating_ratio": 0.1942,
        "top10_avg_reviews": 21,
        "top10_avg_rating": 4.76,
        "top10_seller_count": 10,
        "price_min": 166,
        "price_max": 1952
      }
    },
    {
      "category": "车载用品-木质香薰",
      "keyword_ru": "ароматизатор для авто деревянный",
      "keyword_en": "wooden car air freshener",
      "tags": [
        "刚需",
        "全年品",
        "轻小件",
        "高复购"
      ],
      "total_score": 8.5,
      "recommendation": "🔥 强烈推荐入场",
      "blue_ocean_index": 39.0,
      "dimensions": {
        "search_volume": 2,
        "search_volume_detail": "搜索结果312个",
        "avg_reviews": 2,
        "avg_reviews_detail": "TOP10平均评论71条",
        "seller_count": 1,
        "seller_count_detail": "TOP10卖家10家",
        "ozon_self": 1,
        "ozon_self_detail": "自营占比3.7%",
        "price_concentration": 1,
        "price_concentration_detail": "价格集中度0.35",
        "rating_variance": 0.5,
        "rating_variance_detail": "低评分占比17.4%",
        "rFBS_fitness": 1,
        "rFBS_fitness_detail": "标签: 刚需, 全年品, 轻小件, 高复购"
      },
      "metrics": {
        "total_search_results": 312,
        "avg_price": 2221,
        "avg_reviews": 138,
        "avg_rating": 4.54,
        "unique_sellers": 7,
        "ozon_self_ratio": 0.0366,
        "price_concentration": 0.352,
        "low_rating_ratio": 0.1736,
        "top10_avg_reviews": 71,
        "top10_avg_rating": 4.52,
        "top10_seller_count": 10,
        "price_min": 303,
        "price_max": 3757
      }
    },
    {
      "category": "3C电子-无线耳机（红海对照）",
      "keyword_ru": "наушники беспроводные",
      "keyword_en": "wireless earphones",
      "tags": [
        "红海对照",
        "超饱和",
        "不入场"
      ],
      "total_score": 2.5,
      "recommendation": "❌ 建议放弃",
      "blue_ocean_index": 191.34,
      "dimensions": {
        "search_volume": 2,
        "search_volume_detail": "搜索结果14733个",
        "avg_reviews": 0,
        "avg_reviews_detail": "TOP10平均评论796条",
        "seller_count": 0,
        "seller_count_detail": "TOP10卖家28家",
        "ozon_self": 0.5,
        "ozon_self_detail": "自营占比29.8%",
        "price_concentration": 0,
        "price_concentration_detail": "价格集中度0.07",
        "rating_variance": 0,
        "rating_variance_detail": "低评分占比5.6%",
        "rFBS_fitness": 0,
        "rFBS_fitness_detail": "标签: 红海对照, 超饱和, 不入场"
      },
      "metrics": {
        "total_search_results": 14733,
        "avg_price": 270,
        "avg_reviews": 1877,
        "avg_rating": 4.43,
        "unique_sellers": 76,
        "ozon_self_ratio": 0.2981,
        "price_concentration": 0.0741,
        "low_rating_ratio": 0.0564,
        "top10_avg_reviews": 796,
        "top10_avg_rating": 4.26,
        "top10_seller_count": 28,
        "price_min": 91,
        "price_max": 686
      }
    },
    {
      "category": "3C配件-手机壳（红海对照）",
      "keyword_ru": "чехол для телефона",
      "keyword_en": "phone case",
      "tags": [
        "红海对照",
        "超饱和",
        "不入场"
      ],
      "total_score": 2,
      "recommendation": "❌ 建议放弃",
      "blue_ocean_index": 273.96,
      "dimensions": {
        "search_volume": 2,
        "search_volume_detail": "搜索结果19451个",
        "avg_reviews": 0,
        "avg_reviews_detail": "TOP10平均评论1962条",
        "seller_count": 0,
        "seller_count_detail": "TOP10卖家23家",
        "ozon_self": 0,
        "ozon_self_detail": "自营占比33.9%",
        "price_concentration": 0,
        "price_concentration_detail": "价格集中度0.14",
        "rating_variance": 0,
        "rating_variance_detail": "低评分占比9.3%",
        "rFBS_fitness": 0,
        "rFBS_fitness_detail": "标签: 红海对照, 超饱和, 不入场"
      },
      "metrics": {
        "total_search_results": 19451,
        "avg_price": 295,
        "avg_reviews": 1327,
        "avg_rating": 4.24,
        "unique_sellers": 70,
        "ozon_self_ratio": 0.3386,
        "price_concentration": 0.135,
        "low_rating_ratio": 0.093,
        "top10_avg_reviews": 1962,
        "top10_avg_rating": 4.09,
        "top10_seller_count": 23,
        "price_min": 98,
        "price_max": 1137
      }
    },
    {
      "category": "宠物服饰-犬冬装（红海对照）",
      "keyword_ru": "зимняя одежда для собак",
      "keyword_en": "winter dog clothes",
      "tags": [
        "红海对照",
        "退货率高",
        "不入场"
      ],
      "total_score": 2,
      "recommendation": "❌ 建议放弃",
      "blue_ocean_index": 232.35,
      "dimensions": {
        "search_volume": 2,
        "search_volume_detail": "搜索结果18820个",
        "avg_reviews": 0,
        "avg_reviews_detail": "TOP10平均评论1318条",
        "seller_count": 0,
        "seller_count_detail": "TOP10卖家21家",
        "ozon_self": 0,
        "ozon_self_detail": "自营占比33.2%",
        "price_concentration": 0,
        "price_concentration_detail": "价格集中度0.06",
        "rating_variance": 0,
        "rating_variance_detail": "低评分占比7.0%",
        "rFBS_fitness": 0,
        "rFBS_fitness_detail": "标签: 红海对照, 退货率高, 不入场"
      },
      "metrics": {
        "total_search_results": 18820,
        "avg_price": 621,
        "avg_reviews": 2289,
        "avg_rating": 4.15,
        "unique_sellers": 80,
        "ozon_self_ratio": 0.3321,
        "price_concentration": 0.0626,
        "low_rating_ratio": 0.0701,
        "top10_avg_reviews": 1318,
        "top10_avg_rating": 4.14,
        "top10_seller_count": 21,
        "price_min": 159,
        "price_max": 2585
      }
    }
  ],
  "alerts": [
    {
      "type": "🟢 新蓝海发现",
      "category": "宠物智能-猫饮水机",
      "message": "「宠物智能-猫饮水机」蓝海评分11分，强烈推荐入场！",
      "score": 11,
      "priority": "high"
    },
    {
      "type": "🟢 新蓝海发现",
      "category": "宠物清洁-除毛工具",
      "message": "「宠物清洁-除毛工具」蓝海评分11分，强烈推荐入场！",
      "score": 11,
      "priority": "high"
    },
    {
      "type": "🟢 新蓝海发现",
      "category": "家居收纳-冰箱收纳盒",
      "message": "「家居收纳-冰箱收纳盒」蓝海评分11分，强烈推荐入场！",
      "score": 11,
      "priority": "high"
    },
    {
      "type": "🟢 新蓝海发现",
      "category": "厨房工具-食物温度计",
      "message": "「厨房工具-食物温度计」蓝海评分11分，强烈推荐入场！",
      "score": 11,
      "priority": "high"
    },
    {
      "type": "🟢 新蓝海发现",
      "category": "厨房工具-多功能切菜器",
      "message": "「厨房工具-多功能切菜器」蓝海评分11分，强烈推荐入场！",
      "score": 11,
      "priority": "high"
    },
    {
      "type": "🟢 新蓝海发现",
      "category": "车载冬季-加热毯",
      "message": "「车载冬季-加热毯」蓝海评分11分，强烈推荐入场！",
      "score": 11,
      "priority": "high"
    },
    {
      "type": "🟢 新蓝海发现",
      "category": "车载夏季-冰丝方向盘套",
      "message": "「车载夏季-冰丝方向盘套」蓝海评分11分，强烈推荐入场！",
      "score": 11,
      "priority": "high"
    },
    {
      "type": "🟢 新蓝海发现",
      "category": "智能穿戴-健身手环",
      "message": "「智能穿戴-健身手环」蓝海评分11分，强烈推荐入场！",
      "score": 11,
      "priority": "high"
    },
    {
      "type": "🟢 新蓝海发现",
      "category": "智能穿戴-儿童定位手表",
      "message": "「智能穿戴-儿童定位手表」蓝海评分11分，强烈推荐入场！",
      "score": 11,
      "priority": "high"
    },
    {
      "type": "🟢 新蓝海发现",
      "category": "园艺智能-植物生长灯",
      "message": "「园艺智能-植物生长灯」蓝海评分11分，强烈推荐入场！",
      "score": 11,
      "priority": "high"
    },
    {
      "type": "🟢 新蓝海发现",
      "category": "园艺装饰-太阳能户外灯",
      "message": "「园艺装饰-太阳能户外灯」蓝海评分11分，强烈推荐入场！",
      "score": 11,
      "priority": "high"
    },
    {
      "type": "🟢 新蓝海发现",
      "category": "户外休闲-便携吊床",
      "message": "「户外休闲-便携吊床」蓝海评分11分，强烈推荐入场！",
      "score": 11,
      "priority": "high"
    },
    {
      "type": "🟢 新蓝海发现",
      "category": "益智玩具-磁力片",
      "message": "「益智玩具-磁力片」蓝海评分11分，强烈推荐入场！",
      "score": 11,
      "priority": "high"
    },
    {
      "type": "🟢 新蓝海发现",
      "category": "益智玩具-科学实验套装",
      "message": "「益智玩具-科学实验套装」蓝海评分11分，强烈推荐入场！",
      "score": 11,
      "priority": "high"
    },
    {
      "type": "🟢 新蓝海发现",
      "category": "夏季刚需-防晒渔夫帽",
      "message": "「夏季刚需-防晒渔夫帽」蓝海评分11分，强烈推荐入场！",
      "score": 11,
      "priority": "high"
    },
    {
      "type": "🟢 新蓝海发现",
      "category": "宠物智能-猫喂食器",
      "message": "「宠物智能-猫喂食器」蓝海评分10.5分，强烈推荐入场！",
      "score": 10.5,
      "priority": "high"
    },
    {
      "type": "🟢 新蓝海发现",
      "category": "宠物智能-小型犬喂食器",
      "message": "「宠物智能-小型犬喂食器」蓝海评分10.5分，强烈推荐入场！",
      "score": 10.5,
      "priority": "high"
    },
    {
      "type": "🟢 新蓝海发现",
      "category": "宠物玩具-互动类",
      "message": "「宠物玩具-互动类」蓝海评分10.5分，强烈推荐入场！",
      "score": 10.5,
      "priority": "high"
    },
    {
      "type": "🟢 新蓝海发现",
      "category": "车载配件-无线充电手机支架",
      "message": "「车载配件-无线充电手机支架」蓝海评分10.5分，强烈推荐入场！",
      "score": 10.5,
      "priority": "high"
    },
    {
      "type": "🟢 新蓝海发现",
      "category": "智能穿戴-健康智能戒指",
      "message": "「智能穿戴-健康智能戒指」蓝海评分10.5分，强烈推荐入场！",
      "score": 10.5,
      "priority": "high"
    },
    {
      "type": "🟢 新蓝海发现",
      "category": "节日装饰-新年LED灯串",
      "message": "「节日装饰-新年LED灯串」蓝海评分10.5分，强烈推荐入场！",
      "score": 10.5,
      "priority": "high"
    },
    {
      "type": "🟢 新蓝海发现",
      "category": "宠物清洁-猫砂盆支架",
      "message": "「宠物清洁-猫砂盆支架」蓝海评分10分，强烈推荐入场！",
      "score": 10,
      "priority": "high"
    },
    {
      "type": "🟢 新蓝海发现",
      "category": "浴室收纳-折叠置物架",
      "message": "「浴室收纳-折叠置物架」蓝海评分10.0分，强烈推荐入场！",
      "score": 10.0,
      "priority": "high"
    },
    {
      "type": "🟢 新蓝海发现",
      "category": "厨房收纳-迷你沥水架",
      "message": "「厨房收纳-迷你沥水架」蓝海评分10分，强烈推荐入场！",
      "score": 10,
      "priority": "high"
    },
    {
      "type": "🟢 新蓝海发现",
      "category": "家居智能-自动皂液器",
      "message": "「家居智能-自动皂液器」蓝海评分10分，强烈推荐入场！",
      "score": 10,
      "priority": "high"
    },
    {
      "type": "🟢 新蓝海发现",
      "category": "车载收纳-后备箱整理箱",
      "message": "「车载收纳-后备箱整理箱」蓝海评分10.0分，强烈推荐入场！",
      "score": 10.0,
      "priority": "high"
    },
    {
      "type": "🟢 新蓝海发现",
      "category": "园艺工具-迷你套装",
      "message": "「园艺工具-迷你套装」蓝海评分10分，强烈推荐入场！",
      "score": 10,
      "priority": "high"
    },
    {
      "type": "🟢 新蓝海发现",
      "category": "教育用品-书法套装",
      "message": "「教育用品-书法套装」蓝海评分10分，强烈推荐入场！",
      "score": 10,
      "priority": "high"
    },
    {
      "type": "🟢 新蓝海发现",
      "category": "益智玩具-木质拼装",
      "message": "「益智玩具-木质拼装」蓝海评分10分，强烈推荐入场！",
      "score": 10,
      "priority": "high"
    },
    {
      "type": "🟢 新蓝海发现",
      "category": "夏季刚需-便携USB小风扇",
      "message": "「夏季刚需-便携USB小风扇」蓝海评分10分，强烈推荐入场！",
      "score": 10,
      "priority": "high"
    },
    {
      "type": "🟢 新蓝海发现",
      "category": "冬季保暖-加热手套",
      "message": "「冬季保暖-加热手套」蓝海评分10分，强烈推荐入场！",
      "score": 10,
      "priority": "high"
    },
    {
      "type": "🟢 新蓝海发现",
      "category": "厨房工具-调料瓶/罐",
      "message": "「厨房工具-调料瓶/罐」蓝海评分9.5分，强烈推荐入场！",
      "score": 9.5,
      "priority": "high"
    },
    {
      "type": "🟢 新蓝海发现",
      "category": "园艺工具-修剪剪刀",
      "message": "「园艺工具-修剪剪刀」蓝海评分9.5分，强烈推荐入场！",
      "score": 9.5,
      "priority": "high"
    },
    {
      "type": "🟢 新蓝海发现",
      "category": "夏季刚需-驱蚊手环/便携驱蚊器",
      "message": "「夏季刚需-驱蚊手环/便携驱蚊器」蓝海评分9.5分，强烈推荐入场！",
      "score": 9.5,
      "priority": "high"
    },
    {
      "type": "🟢 新蓝海发现",
      "category": "冬季保暖-暖手宝",
      "message": "「冬季保暖-暖手宝」蓝海评分9.5分，强烈推荐入场！",
      "score": 9.5,
      "priority": "high"
    },
    {
      "type": "🟢 新蓝海发现",
      "category": "节日礼品-香薰蜡烛礼盒",
      "message": "「节日礼品-香薰蜡烛礼盒」蓝海评分9.5分，强烈推荐入场！",
      "score": 9.5,
      "priority": "high"
    },
    {
      "type": "🟢 新蓝海发现",
      "category": "车载用品-木质香薰",
      "message": "「车载用品-木质香薰」蓝海评分8.5分，强烈推荐入场！",
      "score": 8.5,
      "priority": "high"
    }
  ],
  "summary": {
    "total_categories": 40,
    "strong_recommend": 37,
    "conditional": 0,
    "avoid": 3,
    "avg_score": 9.76
  }
}